termai/__init__.py
termai/cli.py
termai/termchat.py
termai/termpics.py
termai-0.1.1.1.1.dist-info/METADATA
termai-0.1.1.1.1.dist-info/WHEEL
termai-0.1.1.1.1.dist-info/entry_points.txt
termai-0.1.1.1.1.dist-info/top_level.txt
termai-0.1.1.1.1.dist-info/RECORD
